Dimv/Dimv.py
Dimv/__init__.py
Dimv/download.py
Dimv/download_folder.py
Dimv/parse_url.py
Dimv-0.0.2.1.dist-info/LICENSE.txt
Dimv-0.0.2.1.dist-info/METADATA
Dimv-0.0.2.1.dist-info/WHEEL
Dimv-0.0.2.1.dist-info/top_level.txt
Dimv-0.0.2.1.dist-info/RECORD
