Metadata-Version: 2.1
Name: Dimv
Version: 0.0.2.1
Summary: An extension of gdown
Home-page: https://github.com/Vermylion/Dimv
Author: Guillaume Quarmeau
Author-email: vermylioncode@gmail.com
Project-URL: Bug Tracker, https://github.com/Vermylion/Dimv
Classifier: Programming Language :: Python :: 3
Classifier: License :: OSI Approved :: MIT License
Classifier: Operating System :: OS Independent
Requires-Python: >=3.6
License-File: LICENSE.txt
Requires-Dist: gdown
Requires-Dist: google-auth-oauthlib
Requires-Dist: google
Requires-Dist: google-api-python-client
